{"data_format":1,"data_url":"https://nominatim.openstreetmap.org/taginfo.json","project":{"name":"Nominatim","description":"OSM search engine.","project_url":"https://nominatim.openstreetmap.org","doc_url":"https://nominatim.org/release-docs/develop/","contact_name":"Sarah Hoffmann","contact_email":"lonvia@denofr.de"},"tags":[{"key":"historic","description":"POI/feature in the search database (except for values: yes, no)."},{"key":"military","description":"POI/feature in the search database (except for values: yes, no)."},{"key":"man_made","description":"POI/feature in the search database"},{"key":"landuse","description":"POI/feature in the search database"},{"key":"place","description":"POI/feature in the search database"},{"key":"highway","description":"POI/feature in the search database (except for values: no, turning_circle, mini_roundabout, noexit, crossing, give_way, stop)."},{"key":"waterway","description":"POI/feature in the search database (except for values: riverbank)."},{"key":"natural","description":"POI/feature in the search database (except for values: yes, no, coastline)."},{"key":"mountain_pass","description":"POI/feature in the search database (except for values: no)."},{"key":"healthcare","description":"POI/feature in the search database"},{"key":"club","description":"POI/feature in the search database (except for values: no)."},{"key":"bridge","description":"POI/feature in the search database (except for values: no)."},{"key":"leisure","description":"POI/feature in the search database (except for values: no)."},{"key":"emergency","description":"POI/feature in the search database (except for values: yes, no, fire_hydrant)."},{"key":"building","description":"POI/feature in the search database (except for values: no)."},{"key":"office","description":"POI/feature in the search database (except for values: no)."},{"key":"aeroway","description":"POI/feature in the search database (except for values: no)."},{"key":"railway","description":"POI/feature in the search database (except for values: level_crossing, no, rail, switch, abandoned, signal, buffer_stop, razed)."},{"key":"craft","description":"POI/feature in the search database (except for values: no)."},{"key":"junction","description":"POI/feature in the search database"},{"key":"tunnel","description":"POI/feature in the search database (except for values: no)."},{"key":"shop","description":"POI/feature in the search database (except for values: no)."},{"key":"tourism","description":"POI/feature in the search database (except for values: yes, no)."},{"key":"amenity","description":"POI/feature in the search database (except for values: no, parking_space, parking_entrance)."},{"key":"boundary","description":"POI/feature in the search database (except for values: place, land_area)."},{"key":"aerialway","description":"POI/feature in the search database (except for values: pylon, no)."},{"key":"int_ref","description":"Searchable name of the place."},{"key":"loc_name","description":"Searchable name of the place."},{"key":"pcode","description":"Searchable name of the place."},{"key":"addr:housename","description":"Searchable name of the place."},{"key":"old_name","description":"Searchable name of the place."},{"key":"name","description":"Searchable name of the place."},{"key":"short_name","description":"Searchable name of the place."},{"key":"brand","description":"Searchable name of the place."},{"key":"ref","description":"Searchable name of the place."},{"key":"reg_ref","description":"Searchable name of the place."},{"key":"reg_name","description":"Searchable name of the place."},{"key":"old_ref","description":"Searchable name of the place."},{"key":"loc_ref","description":"Searchable name of the place."},{"key":"iata","description":"Searchable name of the place."},{"key":"ISO3166-2","description":"Searchable name of the place."},{"key":"nat_name","description":"Searchable name of the place."},{"key":"alt_name","description":"Searchable name of the place."},{"key":"official_name","description":"Searchable name of the place."},{"key":"icao","description":"Searchable name of the place."},{"key":"nat_ref","description":"Searchable name of the place."},{"key":"int_name","description":"Searchable name of the place."},{"key":"place_name","description":"Searchable name of the place."},{"key":"tiger:zip_right","description":"Used to determine the address of a place."},{"key":"tiger:county","description":"Used to determine the address of a place."},{"key":"addr:country_code","description":"Used to determine the address of a place."},{"key":"postal_code","description":"Used to determine the address of a place."},{"key":"addr:housenumber","description":"Used to determine the address of a place."},{"key":"is_in","description":"Used to determine the address of a place."},{"key":"addr","description":"Used to determine the address of a place."},{"key":"is_in:country_code","description":"Used to determine the address of a place."},{"key":"is_in:country","description":"Used to determine the address of a place."},{"key":"postcode","description":"Used to determine the address of a place."},{"key":"addr:country","description":"Used to determine the address of a place."},{"key":"addr:streetnumber","description":"Used to determine the address of a place."},{"key":"addr:postcode","description":"Used to determine the address of a place."},{"key":"tiger:zip_left","description":"Used to determine the address of a place."},{"key":"addr:conscriptionnumber","description":"Used to determine the address of a place."},{"key":"country_code","description":"Used to determine the address of a place."},{"key":"ISO3166-1","description":"Used to determine the address of a place."},{"key":"addr:interpolation","description":"Used to determine the address of a place."}]}
